api/__init__.py
api/matrix_client.py
api/photodna_client.py
data/__init__.py
data/base.py
data/monitor_persistence.py
helpers/__init__.py
helpers/extract_links_from_markdown.py
helpers/fetch_image.py
helpers/spam_image_bootstrapper.py
ml/__init__.py
ml/bag_of_words.py
ml/classifier.py
processors/__init__.py
processors/account_age_processor.py
processors/base.py
processors/blacklist_processor.py
processors/mime_processor.py
processors/phash_processor.py
processors/photodna_processor.py
processors/spam_image_processor.py
processors/title_conformity_processor.py
processors/toxicity_processor.py
processors/user_processor.py
lemmymodbot_test-0.5.0.dist-info/METADATA
lemmymodbot_test-0.5.0.dist-info/WHEEL
lemmymodbot_test-0.5.0.dist-info/top_level.txt
lemmymodbot_test-0.5.0.dist-info/RECORD
